LICENSE
README.md
setup.cfg
setup.py
src/HCP_Packer.egg-info/PKG-INFO
src/HCP_Packer.egg-info/SOURCES.txt
src/HCP_Packer.egg-info/dependency_links.txt
src/HCP_Packer.egg-info/requires.txt
src/HCP_Packer.egg-info/top_level.txt
src/hcp_packer/__init__.py
src/hcp_packer/client.py