Metadata-Version: 2.1
Name: HCP-Packer
Version: 0.0.13
Summary: HCP Packer API Client
Home-page: https://kba-it.com
Author: KBA IT
Author-email: info@kba-it.com
License: MIT
Project-URL: Source, https://github.com/KBA-IT/hcp-packer
Keywords: Hashicorp Packer
License-File: LICENSE
